pilyso_io/__init__.py
pilyso_io/imagestack/__init__.py
pilyso_io/imagestack/imagestack.py
pilyso_io/imagestack/util.py
pilyso_io/imagestack/readers/__init__.py
pilyso_io/imagestack/readers/czi.py
pilyso_io/imagestack/readers/nd2.py
pilyso_io/imagestack/readers/ndip.py
pilyso_io/imagestack/readers/ometiff.py
pilyso_io/imagestack/readers/tiff.py
pilyso_io-0.0.1.dev4.dist-info/LICENSE.rst
pilyso_io-0.0.1.dev4.dist-info/METADATA
pilyso_io-0.0.1.dev4.dist-info/WHEEL
pilyso_io-0.0.1.dev4.dist-info/top_level.txt
pilyso_io-0.0.1.dev4.dist-info/RECORD
