Metadata-Version: 2.1
Name: pilyso-io
Version: 0.0.1.dev4
Summary: pilyso - image reading library
Home-page: https://github.com/modsim/pilyso-io
Author: Christian Sachs
Author-email: c.sachs@fz-juelich.de
License: BSD
Platform: UNKNOWN
Classifier: Development Status :: 4 - Beta
Classifier: Intended Audience :: Science/Research
Classifier: License :: OSI Approved :: BSD License
Classifier: Operating System :: POSIX
Classifier: Operating System :: POSIX :: Linux
Classifier: Operating System :: MacOS :: MacOS X
Classifier: Operating System :: Microsoft :: Windows
Classifier: Programming Language :: Python :: 3
Classifier: Topic :: Software Development :: Libraries
Classifier: Topic :: Scientific/Engineering :: Bio-Informatics
Requires-Dist: numpy
Requires-Dist: nd2file
Requires-Dist: tifffile
Requires-Dist: czifile
Provides-Extra: ndip
Requires-Dist: opencv ; extra == 'ndip'
